slicer_package_manager/__init__.py
slicer_package_manager/_version.py
slicer_package_manager/constants.py
slicer_package_manager/utilities.py
slicer_package_manager/api/__init__.py
slicer_package_manager/api/app.py
slicer_package_manager/models/__init__.py
slicer_package_manager/models/extension.py
slicer_package_manager/models/package.py
tests/__init__.py
tests/conftest.py
tests/test_load.py
tests/test_slicer_package_manager.py
slicer_package_manager-0.9.0.dist-info/AUTHORS.rst
slicer_package_manager-0.9.0.dist-info/LICENSE
slicer_package_manager-0.9.0.dist-info/METADATA
slicer_package_manager-0.9.0.dist-info/WHEEL
slicer_package_manager-0.9.0.dist-info/entry_points.txt
slicer_package_manager-0.9.0.dist-info/top_level.txt
slicer_package_manager-0.9.0.dist-info/RECORD
