Metadata-Version: 2.1
Name: slicer-package-manager
Version: 0.9.0
Summary: Manage Slicer application and extension packages.
Author-email: Pierre Assemat <pierre.assemat@kitware.com>, Jean-Christophe Fillion-Robin <jchris.fillionr@kitware.com>
Maintainer-email: Jean-Christophe Fillion-Robin <jchris.fillionr@kitware.com>
Project-URL: Documentation, https://slicer-package-manager.readthedocs.io
Project-URL: Source, https://github.com/girder/slicer_package_manager
Keywords: girder-plugin,slicer_package_manager
Classifier: Development Status :: 5 - Production/Stable
Classifier: License :: OSI Approved :: Apache Software License
Classifier: Natural Language :: English
Classifier: Programming Language :: Python :: 3
Requires-Python: >=3.8
License-File: LICENSE
License-File: AUTHORS.rst
Requires-Dist: girder ~=3.1.20
Requires-Dist: girder-hashsum-download ~=3.1.20
Requires-Dist: html-sanitizer >=2.4.1
Provides-Extra: test
Requires-Dist: pytest ~=7.4.0 ; extra == 'test'
Requires-Dist: pytest-girder ~=3.1.20 ; extra == 'test'
Requires-Dist: pytest-lazy-fixture ; extra == 'test'
Requires-Dist: tox ; extra == 'test'
Requires-Dist: virtualenv ; extra == 'test'
Requires-Dist: ruff ; extra == 'test'
